Metadata-Version: 1.1
Name: Flask-ThriftClient
Version: 0.2.0
Summary: Adds thrift client support to your Flask application
Home-page: https://bitbucket.org/chub/flask-thriftclient
Author: Pierre Lamot
Author-email: pierre.lamot@yahoo.fr
License: BSD
Platform: any
Classifier: Development Status :: 4 - Beta
Classifier: Environment :: Web Environment
Classifier: Intended Audience :: Developers
Classifier: Framework :: Flask
Classifier: License :: OSI Approved :: BSD License
Classifier: Intended Audience :: Developers
Classifier: Operating System :: OS Independent
Classifier: Programming Language :: Python :: 2 :: Only
Classifier: Topic :: Internet :: WWW/HTTP :: Dynamic Content
Classifier: Topic :: Software Development :: Libraries :: Python Modules
